Metadata-Version: 2.1
Name: enta
Version: 0.0.1
Summary: Excel数字转列字母
Home-page: UNKNOWN
Author: ireman
Author-email: z_fsong@163.com
License: UNKNOWN
Platform: UNKNOWN
Classifier: Programming Language :: Python :: 3
Classifier: License :: OSI Approved :: Apache Software License
Classifier: Operating System :: OS Independent
